{"proxies":{"ti.systemnavigationbar.ExampleProxy":{"superPackageName":"org.appcelerator.titanium.proxy","methods":{"printMessage":{"runOnUiThread":false,"hasInvocation":false,"args":[{"converter":"org.appcelerator.kroll.KrollConverter","defaultValueProvider":"org.appcelerator.kroll.KrollConverter","name":"message","sourceName":"message","type":"java.lang.String"}],"apiName":"printMessage","converter":"org.appcelerator.kroll.KrollConverter","defaultValueProvider":"org.appcelerator.kroll.KrollConverter","name":"__default_name__","returnType":"void"},"getMessage":{"runOnUiThread":false,"hasInvocation":false,"args":[],"apiName":"getMessage","converter":"org.appcelerator.kroll.KrollConverter","defaultValueProvider":"org.appcelerator.kroll.KrollConverter","name":"__default_name__","returnType":"java.lang.String"},"setMessage":{"runOnUiThread":false,"hasInvocation":false,"args":[{"converter":"org.appcelerator.kroll.KrollConverter","defaultValueProvider":"org.appcelerator.kroll.KrollConverter","name":"message","sourceName":"message","type":"java.lang.String"}],"apiName":"setMessage","converter":"org.appcelerator.kroll.KrollConverter","defaultValueProvider":"org.appcelerator.kroll.KrollConverter","name":"__default_name__","returnType":"void"}},"dynamicProperties":{"message":{"set":true,"nativeConverter":"org.appcelerator.kroll.KrollConverter","getMethodName":"getMessage","setMethodName":"setMessage","setMethodArgs":[{"converter":"org.appcelerator.kroll.KrollConverter","defaultValueProvider":"org.appcelerator.kroll.KrollConverter","name":"message","sourceName":"message","type":"java.lang.String"}],"setDefaultProviders":["org.appcelerator.kroll.KrollConverter"],"converter":"org.appcelerator.kroll.KrollConverter","defaultValueProvider":"org.appcelerator.kroll.KrollConverter","retain":true,"javascriptConverter":"org.appcelerator.kroll.KrollConverter","getHasInvocation":false,"runOnUiThread":false,"getMethodArgs":[],"getReturnType":"java.lang.String","setReturnType":"void","get":true,"name":"message","setHasInvocation":false,"getDefaultProviders":[]}},"superProxyBindingClassName":"org.appcelerator.titanium.proxy.TiViewProxyBindingGen","proxyClassName":"ExampleProxy","proxyAttrs":{"propertyAccessors":[],"fullAPIName":"Systemnavigationbar.Example","name":"Example","proxyClassName":"ti.systemnavigationbar.ExampleProxy","isTopLevel":false,"id":"ti.systemnavigationbar.ExampleProxy","creatableInModule":"ti.systemnavigationbar.SystemnavigationbarModule","parentModule":"org.appcelerator.kroll.annotations.Kroll.DEFAULT"},"packageName":"ti.systemnavigationbar","sourceName":"ti.systemnavigationbar.ExampleProxyBindingGen","superProxyClassName":"TiViewProxy","isModule":false,"genClassName":"ExampleProxyBindingGen"},"ti.systemnavigationbar.SystemnavigationbarModule":{"superPackageName":"org.appcelerator.kroll","methods":{"setStatusBarColor":{"runOnUiThread":false,"hasInvocation":false,"args":[{"converter":"org.appcelerator.kroll.KrollConverter","defaultValueProvider":"org.appcelerator.kroll.KrollConverter","name":"color","sourceName":"color","type":"java.lang.String"}],"apiName":"setStatusBarColor","converter":"org.appcelerator.kroll.KrollConverter","defaultValueProvider":"org.appcelerator.kroll.KrollConverter","name":"__default_name__","returnType":"void"},"setNavigationBarColor":{"runOnUiThread":false,"hasInvocation":false,"args":[{"converter":"org.appcelerator.kroll.KrollConverter","defaultValueProvider":"org.appcelerator.kroll.KrollConverter","name":"color","sourceName":"color","type":"java.lang.String"}],"apiName":"setNavigationBarColor","converter":"org.appcelerator.kroll.KrollConverter","defaultValueProvider":"org.appcelerator.kroll.KrollConverter","name":"__default_name__","returnType":"void"},"hideSystemNavigationbar":{"runOnUiThread":false,"hasInvocation":false,"args":[],"apiName":"hideSystemNavigationbar","converter":"org.appcelerator.kroll.KrollConverter","defaultValueProvider":"org.appcelerator.kroll.KrollConverter","name":"__default_name__","returnType":"void"}},"superProxyBindingClassName":"org.appcelerator.kroll.KrollModuleBindingGen","proxyClassName":"SystemnavigationbarModule","proxyAttrs":{"propertyAccessors":[],"fullAPIName":"Systemnavigationbar","name":"Systemnavigationbar","proxyClassName":"ti.systemnavigationbar.SystemnavigationbarModule","isTopLevel":false,"id":"ti.systemnavigationbar"},"packageName":"ti.systemnavigationbar","sourceName":"ti.systemnavigationbar.SystemnavigationbarModuleBindingGen","superProxyClassName":"KrollModule","isModule":true,"genClassName":"SystemnavigationbarModuleBindingGen","onAppCreate":"onAppCreate"}},"modules":{"ti.systemnavigationbar.SystemnavigationbarModule":{"apiName":"Systemnavigationbar","createProxies":[{"propertyAccessors":[],"fullAPIName":"Systemnavigationbar.Example","name":"Example","proxyClassName":"ti.systemnavigationbar.ExampleProxy","isTopLevel":false,"id":"ti.systemnavigationbar.ExampleProxy","creatableInModule":"ti.systemnavigationbar.SystemnavigationbarModule","parentModule":"org.appcelerator.kroll.annotations.Kroll.DEFAULT"}]}}}